embedding_ada/__init__.py
embedding_ada/adapter.py
embedding_ada/adapter_embedding.py
embedding_ada/base_finetune_engine.py
embedding_ada/embedding_model.py
embedding_ada/fine_tune_engine.py
embedding_ada/synthetic_dataset.py
embedding_ada/train_model.py
embedding_ada/two_layer_cnn.py
embedding_ada-0.1.9.dist-info/LICENSE
embedding_ada-0.1.9.dist-info/METADATA
embedding_ada-0.1.9.dist-info/WHEEL
embedding_ada-0.1.9.dist-info/top_level.txt
embedding_ada-0.1.9.dist-info/RECORD
