Metadata-Version: 2.1
Name: embedding-ada
Version: 0.1.9
Summary: Python Package to Train Embedding adapter on top of any Embedding models from Hugging face and OpenAI
Author: Pavan Kumar Medarametla
Author-email: pavankumarchowdary35@gmail.com
License: MIT
Classifier: Programming Language :: Python :: 3
Classifier: License :: OSI Approved :: MIT License
Classifier: Operating System :: OS Independent
Requires-Python: >=3.6
License-File: LICENSE
Requires-Dist: langchain
Requires-Dist: langchain-community
Requires-Dist: langchain-core
Requires-Dist: llama-index
Requires-Dist: llama-index-core
Requires-Dist: llama-index-embeddings-adapter
Requires-Dist: llama-index-embeddings-huggingface
Requires-Dist: llama-index-embeddings-langchain
Requires-Dist: llama-index-embeddings-openai
Requires-Dist: llama-index-finetuning
Requires-Dist: llama-index-llms-azure-openai
Requires-Dist: llama-index-embeddings-azure-openai
Requires-Dist: llama-index-llms-openai
Requires-Dist: openai
Requires-Dist: pydantic
Requires-Dist: sentence-transformers
Requires-Dist: tqdm
Requires-Dist: transformers
Requires-Dist: setuptools
Requires-Dist: twine
Requires-Dist: wheel
